flask_pydantic_serializers/__init__.py
flask_pydantic_serializers/base.py
flask_pydantic_serializers/json_mixin.py
flask_pydantic_serializers/timestamps.py
flask_pydantic_serializers-1.0.0.dist-info/METADATA
flask_pydantic_serializers-1.0.0.dist-info/WHEEL
flask_pydantic_serializers-1.0.0.dist-info/top_level.txt
flask_pydantic_serializers-1.0.0.dist-info/RECORD
